{
  "generatedAt": "2026-07-23T16:49:39.994Z",
  "version": "v2-contract",
  "base": "http://127.0.0.1:8090",
  "routes": {
    "GET /api/org/empresa": {
      "method": "GET",
      "path": "/api/org/empresa",
      "tag": "Organização",
      "contractKind": "list",
      "checks": {
        "no_auth_401": {
          "ok": true,
          "detail": "HTTP 401",
          "classification": null
        },
        "invalid_token_401": {
          "ok": true,
          "detail": "HTTP 401",
          "classification": null
        },
        "wrong_tenant_403": {
          "ok": true,
          "detail": "HTTP 403",
          "classification": null
        },
        "success_auth": {
          "ok": true,
          "detail": "HTTP 200 16ms",
          "classification": null
        },
        "schema_valid": {
          "ok": true,
          "detail": "HTTP 200",
          "classification": null
        },
        "no_sensitive_leak": {
          "ok": true,
          "detail": "OK",
          "classification": null
        }
      }
    },
    "PUT /api/org/empresa": {
      "method": "PUT",
      "path": "/api/org/empresa",
      "tag": "Organização",
      "contractKind": "update",
      "checks": {
        "no_auth_401": {
          "ok": true,
          "detail": "HTTP 401",
          "classification": null
        },
        "invalid_token_401": {
          "ok": true,
          "detail": "HTTP 401",
          "classification": null
        },
        "success_auth": {
          "ok": true,
          "detail": "HTTP 200 37ms",
          "classification": null
        },
        "schema_valid": {
          "ok": true,
          "detail": "HTTP 200",
          "classification": null
        },
        "no_sensitive_leak": {
          "ok": true,
          "detail": "OK",
          "classification": null
        }
      }
    },
    "GET /api/org/setores": {
      "method": "GET",
      "path": "/api/org/setores",
      "tag": "Organização",
      "contractKind": "list",
      "checks": {
        "no_auth_401": {
          "ok": true,
          "detail": "HTTP 401",
          "classification": null
        },
        "invalid_token_401": {
          "ok": true,
          "detail": "HTTP 401",
          "classification": null
        },
        "wrong_tenant_403": {
          "ok": true,
          "detail": "HTTP 403",
          "classification": null
        },
        "success_auth": {
          "ok": true,
          "detail": "HTTP 200 10ms",
          "classification": null
        },
        "schema_valid": {
          "ok": true,
          "detail": "HTTP 200",
          "classification": null
        },
        "no_sensitive_leak": {
          "ok": true,
          "detail": "OK",
          "classification": null
        }
      }
    },
    "POST /api/org/setores": {
      "method": "POST",
      "path": "/api/org/setores",
      "tag": "Organização",
      "contractKind": "create",
      "checks": {
        "no_auth_401": {
          "ok": true,
          "detail": "HTTP 401",
          "classification": null
        },
        "invalid_token_401": {
          "ok": true,
          "detail": "HTTP 401",
          "classification": null
        },
        "success_auth": {
          "ok": true,
          "detail": "HTTP 400 11ms",
          "classification": null
        },
        "schema_valid": {
          "ok": true,
          "detail": "HTTP 400",
          "classification": null
        },
        "no_sensitive_leak": {
          "ok": true,
          "detail": "OK",
          "classification": null
        }
      }
    },
    "DELETE /api/org/setores/:id": {
      "method": "DELETE",
      "path": "/api/org/setores/:id",
      "tag": "Organização",
      "contractKind": "delete",
      "checks": {
        "no_auth_401": {
          "ok": true,
          "detail": "HTTP 401",
          "classification": null
        },
        "invalid_token_401": {
          "ok": true,
          "detail": "HTTP 401",
          "classification": null
        },
        "not_found_404": {
          "ok": true,
          "detail": "HTTP 403",
          "classification": null
        },
        "success_auth": {
          "ok": true,
          "detail": "HTTP 403 14ms",
          "classification": null
        },
        "schema_valid": {
          "ok": true,
          "detail": "HTTP 403",
          "classification": null
        },
        "no_sensitive_leak": {
          "ok": true,
          "detail": "OK",
          "classification": null
        }
      }
    },
    "PUT /api/org/setores/:id": {
      "method": "PUT",
      "path": "/api/org/setores/:id",
      "tag": "Organização",
      "contractKind": "update",
      "checks": {
        "no_auth_401": {
          "ok": true,
          "detail": "HTTP 401",
          "classification": null
        },
        "invalid_token_401": {
          "ok": true,
          "detail": "HTTP 401",
          "classification": null
        },
        "not_found_404": {
          "ok": true,
          "detail": "HTTP 404",
          "classification": null
        },
        "success_auth": {
          "ok": true,
          "detail": "HTTP 404 17ms",
          "classification": null
        },
        "schema_valid": {
          "ok": true,
          "detail": "HTTP 404",
          "classification": null
        },
        "no_sensitive_leak": {
          "ok": true,
          "detail": "OK",
          "classification": null
        }
      }
    },
    "GET /api/org/tree": {
      "method": "GET",
      "path": "/api/org/tree",
      "tag": "Organização",
      "contractKind": "list",
      "checks": {
        "no_auth_401": {
          "ok": true,
          "detail": "HTTP 401",
          "classification": null
        },
        "invalid_token_401": {
          "ok": true,
          "detail": "HTTP 401",
          "classification": null
        },
        "wrong_tenant_403": {
          "ok": true,
          "detail": "HTTP 403",
          "classification": null
        },
        "success_auth": {
          "ok": true,
          "detail": "HTTP 200 94ms",
          "classification": null
        },
        "schema_valid": {
          "ok": true,
          "detail": "HTTP 200",
          "classification": null
        },
        "no_sensitive_leak": {
          "ok": true,
          "detail": "OK",
          "classification": null
        }
      }
    },
    "GET /api/org/unidades": {
      "method": "GET",
      "path": "/api/org/unidades",
      "tag": "Organização",
      "contractKind": "list",
      "checks": {
        "no_auth_401": {
          "ok": true,
          "detail": "HTTP 401",
          "classification": null
        },
        "invalid_token_401": {
          "ok": true,
          "detail": "HTTP 401",
          "classification": null
        },
        "wrong_tenant_403": {
          "ok": true,
          "detail": "HTTP 403",
          "classification": null
        },
        "success_auth": {
          "ok": true,
          "detail": "HTTP 200 19ms",
          "classification": null
        },
        "schema_valid": {
          "ok": true,
          "detail": "HTTP 200",
          "classification": null
        },
        "no_sensitive_leak": {
          "ok": true,
          "detail": "OK",
          "classification": null
        }
      }
    },
    "POST /api/org/unidades": {
      "method": "POST",
      "path": "/api/org/unidades",
      "tag": "Organização",
      "contractKind": "create",
      "checks": {
        "no_auth_401": {
          "ok": true,
          "detail": "HTTP 401",
          "classification": null
        },
        "invalid_token_401": {
          "ok": true,
          "detail": "HTTP 401",
          "classification": null
        },
        "success_auth": {
          "ok": true,
          "detail": "HTTP 400 7ms",
          "classification": null
        },
        "schema_valid": {
          "ok": true,
          "detail": "HTTP 400",
          "classification": null
        },
        "no_sensitive_leak": {
          "ok": true,
          "detail": "OK",
          "classification": null
        }
      }
    },
    "DELETE /api/org/unidades/:id": {
      "method": "DELETE",
      "path": "/api/org/unidades/:id",
      "tag": "Organização",
      "contractKind": "delete",
      "checks": {
        "no_auth_401": {
          "ok": true,
          "detail": "HTTP 401",
          "classification": null
        },
        "invalid_token_401": {
          "ok": true,
          "detail": "HTTP 401",
          "classification": null
        },
        "not_found_404": {
          "ok": true,
          "detail": "HTTP 403",
          "classification": null
        },
        "success_auth": {
          "ok": true,
          "detail": "HTTP 403 16ms",
          "classification": null
        },
        "schema_valid": {
          "ok": true,
          "detail": "HTTP 403",
          "classification": null
        },
        "no_sensitive_leak": {
          "ok": true,
          "detail": "OK",
          "classification": null
        }
      }
    },
    "PUT /api/org/unidades/:id": {
      "method": "PUT",
      "path": "/api/org/unidades/:id",
      "tag": "Organização",
      "contractKind": "update",
      "checks": {
        "no_auth_401": {
          "ok": true,
          "detail": "HTTP 401",
          "classification": null
        },
        "invalid_token_401": {
          "ok": true,
          "detail": "HTTP 401",
          "classification": null
        },
        "not_found_404": {
          "ok": true,
          "detail": "HTTP 404",
          "classification": null
        },
        "success_auth": {
          "ok": true,
          "detail": "HTTP 404 18ms",
          "classification": null
        },
        "schema_valid": {
          "ok": true,
          "detail": "HTTP 404",
          "classification": null
        },
        "no_sensitive_leak": {
          "ok": true,
          "detail": "OK",
          "classification": null
        }
      }
    }
  },
  "classifications": {},
  "summary": {
    "total": 11,
    "passed": 63,
    "failed": 0,
    "actionable": 63,
    "skipped": 12,
    "effectiveFailed": 0
  }
}